LICENSE
README.md
setup.cfg
setup.py
docs/About.rst
docs/Changelog.rst
src/senaite/__init__.py
src/senaite.app.spotlight.egg-info/PKG-INFO
src/senaite.app.spotlight.egg-info/SOURCES.txt
src/senaite.app.spotlight.egg-info/dependency_links.txt
src/senaite.app.spotlight.egg-info/entry_points.txt
src/senaite.app.spotlight.egg-info/namespace_packages.txt
src/senaite.app.spotlight.egg-info/not-zip-safe
src/senaite.app.spotlight.egg-info/requires.txt
src/senaite.app.spotlight.egg-info/top_level.txt
src/senaite/app/__init__.py
src/senaite/app/spotlight/__init__.py
src/senaite/app/spotlight/adapters.py
src/senaite/app/spotlight/configure.zcml
src/senaite/app/spotlight/interfaces.py
src/senaite/app/spotlight/setuphandlers.py
src/senaite/app/spotlight/viewlets.py
src/senaite/app/spotlight/views.py
src/senaite/app/spotlight/profiles/default/metadata.xml
src/senaite/app/spotlight/profiles/default/senaite.app.spotlight.txt
src/senaite/app/spotlight/profiles/uninstall/senaite.core.spotlight.uninstall.txt
src/senaite/app/spotlight/static/js/senaite.app.spotlight.js
src/senaite/app/spotlight/templates/spotlight.pt
src/senaite/app/spotlight/templates/spotlight_trigger_viewlet.pt
src/senaite/app/spotlight/templates/spotlight_viewlet.pt
src/senaite/app/spotlight/upgrades/__init__.py
src/senaite/app/spotlight/upgrades/configure.zcml
src/senaite/app/spotlight/upgrades/handlers.py